Metadata-Version: 2.1
Name: odoo12-addon-l10n-th-withholding-tax-cert
Version: 12.0.1.0.2.99.dev4
Summary: Thai Localization - Withholding Tax Certificate
Home-page: https://github.com/OCA/l10n-thailand/
Author: Ecosoft,Odoo Community Association (OCA)
Author-email: support@odoo-community.org
License: AGPL-3
Platform: UNKNOWN
Classifier: Programming Language :: Python
Classifier: Framework :: Odoo
Classifier: Framework :: Odoo :: 12.0
Classifier: License :: OSI Approved :: GNU Affero General Public License v3
Classifier: Development Status :: 4 - Beta
Requires-Python: >=3.5
Requires-Dist: odoo <12.1dev,>=12.0a
